odoo/addons/ssi_employee_other_duties_assignment/README.rst
odoo/addons/ssi_employee_other_duties_assignment/__init__.py
odoo/addons/ssi_employee_other_duties_assignment/__manifest__.py
odoo/addons/ssi_employee_other_duties_assignment/menu.xml
odoo/addons/ssi_employee_other_duties_assignment/approval_template/employee_other_duties_assignment.xml
odoo/addons/ssi_employee_other_duties_assignment/ir_model_access/employee_other_duties_assignment.xml
odoo/addons/ssi_employee_other_duties_assignment/ir_model_access/employee_other_duties_assignment_type.xml
odoo/addons/ssi_employee_other_duties_assignment/ir_module_category/employee_other_duties_assignment.xml
odoo/addons/ssi_employee_other_duties_assignment/ir_rule/employee_other_duties_assignment.xml
odoo/addons/ssi_employee_other_duties_assignment/ir_sequence/employee_other_duties_assignment.xml
odoo/addons/ssi_employee_other_duties_assignment/models/__init__.py
odoo/addons/ssi_employee_other_duties_assignment/models/employee_other_duties_assignment.py
odoo/addons/ssi_employee_other_duties_assignment/models/employee_other_duties_assignment_type.py
odoo/addons/ssi_employee_other_duties_assignment/models/hr_employee.py
odoo/addons/ssi_employee_other_duties_assignment/policy_template/employee_other_duties_assignment.xml
odoo/addons/ssi_employee_other_duties_assignment/res_group/employee_other_duties_assignment.xml
odoo/addons/ssi_employee_other_duties_assignment/res_group/res_group_data.xml
odoo/addons/ssi_employee_other_duties_assignment/sequence_template/employee_other_duties_assignment.xml
odoo/addons/ssi_employee_other_duties_assignment/static/description/icon.png
odoo/addons/ssi_employee_other_duties_assignment/static/description/icon_timesheet.png
odoo/addons/ssi_employee_other_duties_assignment/views/employee_other_duties_assignment.xml
odoo/addons/ssi_employee_other_duties_assignment/views/employee_other_duties_assignment_type.xml
odoo/addons/ssi_employee_other_duties_assignment/views/hr_employee.xml
odoo14_addon_ssi_employee_other_duties_assignment-14.0.1.0.1.dev1.dist-info/METADATA
odoo14_addon_ssi_employee_other_duties_assignment-14.0.1.0.1.dev1.dist-info/WHEEL
odoo14_addon_ssi_employee_other_duties_assignment-14.0.1.0.1.dev1.dist-info/top_level.txt
odoo14_addon_ssi_employee_other_duties_assignment-14.0.1.0.1.dev1.dist-info/RECORD
